pyjsonnlp/__init__.py
pyjsonnlp/clauses.py
pyjsonnlp/conversion.py
pyjsonnlp/dependencies.py
pyjsonnlp/pipeline.py
pyjsonnlp/tokenization.py
pyjsonnlp/unification.py
pyjsonnlp/util.py
pyjsonnlp/validation.py
pyjsonnlp/validator.py
pyjsonnlp/annotation/__init__.py
pyjsonnlp/annotation/relations.py
pyjsonnlp/microservices/__init__.py
pyjsonnlp/microservices/flask_server.py
pyjsonnlp-0.2.33.data/data/pyjsonnlp/NLP-JSON.schema.json
tests/__init__.py
tests/mocks.py
tests/test_clauses.py
tests/test_conversion.py
tests/test_dependencies.py
tests/test_flask_server.py
tests/test_microservices.py
tests/test_pipeline.py
tests/test_pyjsonnlp.py
tests/test_relations.py
tests/test_tokenization.py
tests/test_unification.py
tests/test_validator.py
pyjsonnlp-0.2.33.dist-info/LICENSE
pyjsonnlp-0.2.33.dist-info/METADATA
pyjsonnlp-0.2.33.dist-info/WHEEL
pyjsonnlp-0.2.33.dist-info/top_level.txt
pyjsonnlp-0.2.33.dist-info/RECORD
