Metadata-Version: 2.1
Name: pyjsonnlp
Version: 0.2.33
Summary: The Python JSON-NLP package
Home-page: https://github.com/dcavar/Py-JSON-NLP
Author: Damir Cavar, Oren Baldinger, Maanvitha Gongalla, Anurag Kumar, Murali Kammili
Author-email: damir@cavar.me
License: UNKNOWN
Platform: UNKNOWN
Classifier: Programming Language :: Python :: 3.6
Classifier: Programming Language :: Python :: 3.7
Classifier: License :: OSI Approved :: Apache Software License
Classifier: Operating System :: OS Independent
Requires-Python: >=3.6
Requires-Dist: conllu (>=1.2.3)
Requires-Dist: jsonschemanlplab (>=3.0.1.1)
Requires-Dist: flask
Requires-Dist: iso639
Requires-Dist: bs4
Requires-Dist: syntok (>=1.1.1)
Requires-Dist: aioify (>=0.3.1)
